sanssouci/__init__.py
sanssouci/lambda_calibration.py
sanssouci/post_hoc_bounds.py
sanssouci/reference_families.py
sanssouci/row_welch.py
sanssouci/version.py
sanssouci-0.1.5.dist-info/licenses/LICENSE
sanssouci-0.1.5.dist-info/METADATA
sanssouci-0.1.5.dist-info/WHEEL
sanssouci-0.1.5.dist-info/top_level.txt
sanssouci-0.1.5.dist-info/RECORD
