Metadata-Version: 2.4
Name: sanssouci
Version: 0.1.5
Summary: Post hoc inference via multiple testing
Author: Alexandre Blain, Nicolas Enjalbert Courrech, Nils Peyrouset
Author-email: Pierre Neuvial <pierre.neuvial@math.univ-toulouse.fr>, Laurent Risser <laurent.risser@math.univ-toulouse.fr>, Bertrand Thirion <bertrand.thirion@inria.fr>
Maintainer-email: Pierre Neuvial <pierre.neuvial@math.univ-toulouse.fr>
License-Expression: GPL-3.0-or-later
Project-URL: Homepage, https://github.com/sanssouci-org/sanssouci.python
Project-URL: Issues, https://github.com/sanssouci-org/sanssouci.python/issues
Classifier: Programming Language :: Python :: 3
Classifier: Operating System :: OS Independent
Requires-Python: >=3.10
License-File: LICENSE
Requires-Dist: joblib<2,>=1.2.0
Requires-Dist: numpy<3,>=1.25
Requires-Dist: scikit-learn<1.9,>=1.5
Requires-Dist: scipy<2,>=1.9.2
Dynamic: license-file
